README
setup.py
pig/__init__.py
pig/base.py
pig/devices.py
pig.egg-info/PKG-INFO
pig.egg-info/SOURCES.txt
pig.egg-info/dependency_links.txt
pig.egg-info/top_level.txt