Metadata-Version: 1.1
Name: pig
Version: 0.1.1
Summary: Phoenix Interfaces for Gadgets
Home-page: https://github.com/erikperillo/pig
Author: Erik Perillo
Author-email: erik.perillo@gmail.com
License: GPL
Platform: UNKNOWN
Classifier: Programming Language :: Python :: 3
